./.gitignore
./Dockerfile
./LICENSE
./PKG-INFO
./README.md
./audio_server.py
./audio_server_exp.py
./audio_server_exp2.py
./mcp-config.json
./pyproject.toml
./requirements.txt
./setup_mcp.py
./simple_test.py
./smithery.yaml
./test_server.py
iflow_mcp_gongrzhe_audio_mcp_server-0.1.0.dist-info/METADATA
iflow_mcp_gongrzhe_audio_mcp_server-0.1.0.dist-info/WHEEL
iflow_mcp_gongrzhe_audio_mcp_server-0.1.0.dist-info/entry_points.txt
iflow_mcp_gongrzhe_audio_mcp_server-0.1.0.dist-info/licenses/LICENSE
iflow_mcp_gongrzhe_audio_mcp_server-0.1.0.dist-info/RECORD
