Metadata-Version: 2.4
Name: iflow-mcp_gongrzhe_audio-mcp-server
Version: 0.1.0
Summary: An MCP server that provides audio input/output capabilities for AI assistants
License-File: LICENSE
Requires-Python: >=3.8
Requires-Dist: google-generativeai>=0.3.0
Requires-Dist: mcp[cli]>=1.2.0
Requires-Dist: numpy>=1.20.0
Requires-Dist: sounddevice>=0.4.5
Requires-Dist: soundfile>=0.10.3
